pts_keysight_e36154a_psu/__init__.py
pts_keysight_e36154a_psu/keysight_E36154A_psu.py
pts_keysight_e36154a_psu-0.0.4.dist-info/LICENSE.txt
pts_keysight_e36154a_psu-0.0.4.dist-info/METADATA
pts_keysight_e36154a_psu-0.0.4.dist-info/WHEEL
pts_keysight_e36154a_psu-0.0.4.dist-info/top_level.txt
pts_keysight_e36154a_psu-0.0.4.dist-info/RECORD
