Metadata-Version: 2.1
Name: pts-keysight-e36154a-psu
Version: 0.0.4
Summary: Keysight E36154A PSU Driver and Diagnostic Package
Home-page: https://gitlab.com/pass-testing-solutions/keysight-e36154a-psu
Author: Pass testing Solutions GmbH
Author-email: shuparna@pass-testing.de
License: MIT
Classifier: License :: OSI Approved :: MIT License
Classifier: Programming Language :: Python :: 3
Classifier: Programming Language :: Python :: 3.9
License-File: LICENSE.txt
Requires-Dist: pyvisa==1.12.0
Requires-Dist: pyvisa-py==0.5.3
Requires-Dist: retry==0.9.2
